annotation_project/__init__.py
annotation_project/annotation_project.py
berrydb/BerryDB.py
berrydb/IngestFileType.py
berrydb/IngestType.py
berrydb/__init__.py
berrydb/berrydb_settings.py
berrydb/eval_metrics.py
berrydb/llm_agent.py
constants/__init__.py
constants/constants.py
database/__init__.py
database/database.py
evaluator/__init__.py
evaluator/berrydb_rag_evaluator.py
fts/__init__.py
fts/fts.py
model_garden/__init__.py
model_garden/annotations_config.py
model_garden/model.py
model_garden/model_config.py
model_garden/model_provider.py
model_garden/model_repo.py
utils/__init__.py
utils/berrydb_init_exception.py
utils/berrydb_metrics.py
utils/utils.py
berrydb-1.6.9.dist-info/METADATA
berrydb-1.6.9.dist-info/WHEEL
berrydb-1.6.9.dist-info/RECORD
