Metadata-Version: 2.1
Name: berrydb
Version: 1.6.9
Summary: The database for unstructured data and AI apps
Home-page: https://berrydb.io
License: Proprietary
Author: BerryDB
Requires-Python: >=3.11,<4.0
Classifier: License :: Other/Proprietary License
Classifier: Programming Language :: Python :: 3
Classifier: Programming Language :: Python :: 3.11
Classifier: Programming Language :: Python :: 3.12
Requires-Dist: requests
